views_pipeline_core/__init__.py
views_pipeline_core/assets/shapefiles/country/ne_110m_admin_0_countries.README.html
views_pipeline_core/assets/shapefiles/country/ne_110m_admin_0_countries.cpg
views_pipeline_core/assets/shapefiles/country/ne_110m_admin_0_countries.dbf
views_pipeline_core/assets/shapefiles/country/ne_110m_admin_0_countries.prj
views_pipeline_core/assets/shapefiles/country/ne_110m_admin_0_countries.shp
views_pipeline_core/assets/shapefiles/country/ne_110m_admin_0_countries.shx
views_pipeline_core/assets/shapefiles/priogrid/priogrid_cell.dbf
views_pipeline_core/assets/shapefiles/priogrid/priogrid_cell.prj
views_pipeline_core/assets/shapefiles/priogrid/priogrid_cell.qpj
views_pipeline_core/assets/shapefiles/priogrid/priogrid_cell.shp
views_pipeline_core/assets/shapefiles/priogrid/priogrid_cell.shx
views_pipeline_core/assets/views_header.png
views_pipeline_core/assets/vpc_header.png
views_pipeline_core/cli/README.md
views_pipeline_core/cli/__init__.py
views_pipeline_core/cli/args.py
views_pipeline_core/cli/utils.py
views_pipeline_core/configs/__init__.py
views_pipeline_core/configs/drift_detection.py
views_pipeline_core/configs/logging.yaml
views_pipeline_core/configs/pipeline.py
views_pipeline_core/data/README.md
views_pipeline_core/data/__init__.py
views_pipeline_core/data/handlers.py
views_pipeline_core/data/utils.py
views_pipeline_core/exceptions/__init__.py
views_pipeline_core/exceptions/exceptions.py
views_pipeline_core/files/README.md
views_pipeline_core/files/__init__.py
views_pipeline_core/files/utils.py
views_pipeline_core/managers/README.md
views_pipeline_core/managers/__init__.py
views_pipeline_core/managers/configuration/README.md
views_pipeline_core/managers/configuration/__init__.py
views_pipeline_core/managers/configuration/configuration.py
views_pipeline_core/managers/ensemble/README.md
views_pipeline_core/managers/ensemble/__init__.py
views_pipeline_core/managers/ensemble/ensemble.py
views_pipeline_core/managers/extractor/README.md
views_pipeline_core-2.2.0.dist-info/METADATA
views_pipeline_core-2.2.0.dist-info/WHEEL
views_pipeline_core-2.2.0.dist-info/RECORD
