Metadata-Version: 2.4
Name: views_pipeline_core
Version: 2.2.0
Summary: 
Author: Borbála Farkas
Author-email: borbala.farkas@pcr.uu.se
Requires-Python: >=3.11,<3.15
Classifier: Programming Language :: Python :: 3
Classifier: Programming Language :: Python :: 3.11
Classifier: Programming Language :: Python :: 3.12
Classifier: Programming Language :: Python :: 3.13
Classifier: Programming Language :: Python :: 3.14
Requires-Dist: appwrite (>=13.4.1,<14.0.0)
Requires-Dist: art (>=6.4,<7.0)
Requires-Dist: geopandas (>=1.0.1,<2.0.0)
Requires-Dist: ingester3 (==2.1.1)
Requires-Dist: markdown (>=3.8.2,<4.0.0)
Requires-Dist: plotly (>=6.0.0,<7.0.0)
Requires-Dist: plotly-express (>=0.4.1,<0.5.0)
Requires-Dist: polars (>=1.34.0,<2.0.0)
Requires-Dist: properscoring (>=0.1,<0.2)
Requires-Dist: pyprojroot (>=0.3.0,<0.4.0)
Requires-Dist: pytest (>=8.3.3,<9.0.0)
Requires-Dist: scipy (>=1.15.1,<2.0.0)
Requires-Dist: seaborn (>=0.13.2,<0.14.0)
Requires-Dist: torch (>=2.6.0,<3.0.0)
Requires-Dist: views-evaluation (>=0.3.0,<0.4.0)
Requires-Dist: views-forecasts (>=0.5.5,<0.6.0)
Requires-Dist: views-transformation-library (>=2.7.2,<3.0.0)
Requires-Dist: viewser (>=6.6.4,<7.0.0)
Requires-Dist: wandb (>=0.18.7,<0.19.0)
